{
  "name": "def",
  "domain": "csam",
  "categories": [
    {
      "name": "DEF",
      "editableStates": [
        "IN_PROGRESS",
        "FOR_CORRECTION"
      ],
      "constraints": [
        {
          "type": "xnor",
          "members": ["safedefModule", "safedefLine", "safedefAddress", "safedefStatus"]
        }
      ],
      "fields": [
        {
          "id": "pointType",
          "type": "text",
          "name_en": "Point Type",
          "name_fr": "Point Type",
          "help_en": "",
          "help_fr": ""
        },
        {
          "id": "safedefModule",
          "type": "text",
          "name_en": "Module",
          "name_fr": "Module",
          "help_en": "",
          "help_fr": ""
        },
        {
          "id": "safedefLine",
          "type": "text",
          "name_en": "Line",
          "name_fr": "Line",
          "help_en": "",
          "help_fr": ""
        },
        {
          "id": "safedefAddress",
          "type": "text",
          "name_en": "Address",
          "name_fr": "Address",
          "help_en": "",
          "help_fr": ""
        },
        {
          "id": "safedefStatus",
          "type": "options",
          "name_en": "Status",
          "name_fr": "Status",
          "help_en": "",
          "help_fr": ""
        }
      ]
    }
  ]
}